kstock/__init__.py
kstock/commands/__init__.py
kstock/commands/dump_tdx_candle_file.py
kstock/common/__init__.py
kstock/common/exception.py
kstock/misc/__init__.py
kstock/misc/trie_tree.py
kstock/stats/__init__.py
kstock/stats/stat_utils.py
kstock/ta/__init__.py
kstock/ta/indicator/__init__.py
kstock/ta/indicator/ema.py
kstock/ta/indicator/macd.py
kstock/tdx/__init__.py
kstock/tdx/block.py
kstock/tdx/candle_loader.py
kstock/tdx/config.py
kstock/tdx/consts.py
kstock/tdx/utils.py
kstock/utils/__init__.py
kstock/utils/decorators.py
kstock-0.0.1.dist-info/LICENSE.txt
kstock-0.0.1.dist-info/METADATA
kstock-0.0.1.dist-info/WHEEL
kstock-0.0.1.dist-info/entry_points.txt
kstock-0.0.1.dist-info/top_level.txt
kstock-0.0.1.dist-info/RECORD
