Metadata-Version: 2.1
Name: kstock
Version: 0.0.1
Summary: A股数据处理工具
Home-page: https://github.com/kkppzzah/kstock
Author: kk
Author-email: kkppzzah@gmail.com
License: MIT
Keywords: A股 通达信文件读取 数据处理
Platform: UNKNOWN
Classifier: Topic :: Office/Business :: Financial
Classifier: License :: OSI Approved :: MIT License
Classifier: Programming Language :: Python :: 3.8
Classifier: Programming Language :: Python :: 3.9
Classifier: Programming Language :: Python :: 3.10
Classifier: Programming Language :: Python :: 3.11
License-File: LICENSE.txt
Requires-Dist: numpy
Requires-Dist: numba
Requires-Dist: pandas
Requires-Dist: environ-config
